desir/__init__.py
desir/commands.json
desir/desir.py
desir/desir3.py
desir/sugar.py
desir-0.691.dist-info/METADATA
desir-0.691.dist-info/WHEEL
desir-0.691.dist-info/top_level.txt
desir-0.691.dist-info/RECORD
