Metadata-Version: 2.1
Name: desir
Version: 0.691
Summary: Python client for Redis key-value store
Home-page: http://github.com/aallamaa/desir
Author: Abdelkader ALLAM
Author-email: abdelkader.allam@gmail.com
Maintainer: Abdelkader ALLAM
Maintainer-email: abdelkader.allam@gmail.com
License: New BSD License
Download-URL: http://www.xone-tech.com/desir/desir-0.691.tar.gz
Keywords: Redis,key-value store
Platform: UNKNOWN
Classifier: Development Status :: 4 - Beta
Classifier: Environment :: Console
Classifier: Intended Audience :: Developers
Classifier: License :: OSI Approved :: BSD License
Classifier: Operating System :: OS Independent
Classifier: Programming Language :: Python
